adhteb/__init__.py
adhteb/benchmarking.py
adhteb/data/.gitkeep
adhteb/data/AD_CDM_JPAD.csv
adhteb/data/cohorts/private/EMIF.csv
adhteb/data/cohorts/private/PREVENT Dementia.csv
adhteb/data/cohorts/private/PREVENT-AD.csv
adhteb/data/cohorts/private/geras/GERAS-I.csv
adhteb/data/cohorts/private/geras/GERAS-II.csv
adhteb/data/cohorts/private/geras/GERAS-J.csv
adhteb/data/cohorts/private/geras/GERAS-US.csv
adhteb/data/cohorts/public/.gitkeep
adhteb/data/cohorts/public/ADNI.csv
adhteb/data/cohorts/public/AMED.csv
adhteb/data/cohorts/public/EPAD.csv
adhteb/data/cohorts/public/NACC.csv
adhteb/leaderboard.py
adhteb/main.py
adhteb/results/AllMiniLM.pkl
adhteb/results/Gemini.pkl
adhteb/results/LinqEmbedMistral.pkl
adhteb/results/OpenAI.pkl
adhteb/results/Qwen38B.pkl
adhteb/results.py
adhteb/utils.py
adhteb/vectorizers.py
adhteb-0.0.6.dist-info/WHEEL
adhteb-0.0.6.dist-info/METADATA
adhteb-0.0.6.dist-info/RECORD
