Metadata-Version: 2.3
Name: adhteb
Version: 0.0.6
Summary: Benchmarking vectorizer performance on Alzheimer's disease concept definitions
Author: Tim Adams, Mehmet Can Ay
Author-email: Tim Adams <tim.adams@scai.fraunhofer.de>, Mehmet Can Ay <mehmet.ay@scai.fraunhofer.de>
License:                                  Apache License
Requires-Dist: cryptography>=46.0.3
Requires-Dist: google-cloud-aiplatform>=1.130.0
Requires-Dist: google-genai>=1.54.0
Requires-Dist: numpy>=2.3.5
Requires-Dist: openai>=2.9.0
Requires-Dist: pandas>=2.3.3
Requires-Dist: pydantic>=2.12.5
Requires-Dist: sentence-transformers>=5.1.2
Requires-Dist: tabulate>=0.9.0
Requires-Python: >=3.11, <4.0
